[
  {
    "id": "1",
    "image": "",
    "name": "DeinTraumHaus",
    "typ": "Haus",
    "address": {
      "street": "Entenstraße",
      "number": "1",
      "PLZ": "60323",
      "city": "Frankfurt am Main",
      "state": "Hessen"
    },
    "exposeURL": "https://google.de",
    "size": "30",
    "source": "Immobilienscout24",
    "contactPerson": "Donald Duck",
    "purchasePrice": "96000",
    "realEstateAgentFees": "3427,2",
    "realEstateTransferTax": "1920",
    "notaryFee": "6240",
    "sumAdditionalPurchaseCost": "11.587,2",
    "overallPurchasePrice": "107.587,2",
    "bankLoan": "107.587,2",
    "initialRepayment": "1,00",
    "interestRate": "1,5",
    "equityCapital": "0",
    "creditRateYear": "2.690",
    "creditRateMonth": "224",
    "netRentYear": " 4800",
    "netRentMonth": "400",
    "maintenanceCostAndImprovementsFactor": "25",
    "managementFeeYear": "300",
    "vacancyRateFactor": "5",
    "pricePerSizeInclAdditionalCost": "3586,24",
    "netRentPerSizePerMonth": "13,33",
    "netRentPerSizePerYear": "159,96",
    "adjustedAnnualNetRent": "3.750" ,
    "adjustedNetReturn": "3,49",
    "maintenanceCostAndImprovementsYear": "750",
    "vacancyRate": "240",
    "improvementsMonth": "",
    "improvementsYear": "",
    "CFBTYear": "820",
    "CFBTMonth": "68"
  },
  {
    "id": "2",
    "image": "",
    "name": "DeinTraumHaus",
    "typ": "Haus",
    "address": {
      "street": "Entenstraße",
      "number": "2",
      "PLZ": "60323",
      "city": "Frankfurt am Main",
      "state": "Hessen"
    },
    "exposeURL": "https://google.de",
    "size": "30",
    "source": "Immobilienscout24",
    "contactPerson": "Donald Duck",
    "purchasePrice": "96000 €",
    "realEstateAgentFees": "3427,2 €",
    "realEstateTransferTax": "1920 €",
    "notaryFee": "6240 €",
    "sumAdditionalPurchaseCost": "11.587,2 €",
    "overallPurchasePrice": "107.587,2 €",
    "bankLoan": "107.587,2 €",
    "initialRepayment": "1,00 %",
    "interestRate": "1,5 %",
    "equityCapital": "0 €",
    "creditRateYear": "2.690 €",
    "creditRateMonth": "224 €",
    "netRentYear": " 4800 €",
    "netRentMonth": "400 €",
    "maintenanceCostAndImprovementsFactor": "25 €",
    "managementFeeYear": "300 €",
    "vacancyRateFactor": "5 %",
    "pricePerSizeInclAdditionalCost": "3586,24 €",
    "netRentPerSizePerMonth": "13,33 €",
    "netRentPerSizePerYear": "159,96 €",
    "adjustedAnnualNetRent": "3.750 €" ,
    "adjustedNetReturn": "3,49 %",
    "maintenanceCostAndImprovementsYear": "750 €",
    "vacancyRate": "240 €",
    "improvementsMonth": "€",
    "improvementsYear": "€",
    "CFBTYear": "820 €",
    "CFBTMonth": "68 €"
  },
  {
    "id": "3",
    "image": "",
    "name": "DeinTraumHaus",
    "typ": "Haus",
    "address": {
      "street": "Entenstraße",
      "number": "3",
      "PLZ": "60323",
      "city": "Frankfurt am Main",
      "state": "Hessen"
    },
    "exposeURL": "https://google.de",
    "size": "30",
    "source": "Immobilienscout24",
    "contactPerson": "Donald Duck",
    "purchasePrice": "96000 €",
    "realEstateAgentFees": "3427,2 €",
    "realEstateTransferTax": "1920 €",
    "notaryFee": "6240 €",
    "sumAdditionalPurchaseCost": "11.587,2 €",
    "overallPurchasePrice": "107.587,2 €",
    "bankLoan": "107.587,2 €",
    "initialRepayment": "1,00 %",
    "interestRate": "1,5 %",
    "equityCapital": "0 €",
    "creditRateYear": "2.690 €",
    "creditRateMonth": "224 €",
    "netRentYear": " 4800 €",
    "netRentMonth": "400 €",
    "maintenanceCostAndImprovementsFactor": "25 €",
    "managementFeeYear": "300 €",
    "vacancyRateFactor": "5 %",
    "pricePerSizeInclAdditionalCost": "3586,24 €",
    "netRentPerSizePerMonth": "13,33 €",
    "netRentPerSizePerYear": "159,96 €",
    "adjustedAnnualNetRent": "3.750 €" ,
    "adjustedNetReturn": "3,49 %",
    "maintenanceCostAndImprovementsYear": "750 €",
    "vacancyRate": "240 €",
    "improvementsMonth": "€",
    "improvementsYear": "€",
    "CFBTYear": "820 €",
    "CFBTMonth": "68 €"
  },
  {
    "id": "4",
    "image": "",
    "name": "DeinTraumHaus",
    "typ": "Haus",
    "address": {
      "street": "Entenstraße",
      "number": "4",
      "PLZ": "60323",
      "city": "Frankfurt am Main",
      "state": "Hessen"
    },
    "exposeURL": "https://google.de",
    "size": "30",
    "source": "Immobilienscout24",
    "contactPerson": "Donald Duck",
    "purchasePrice": "96000 €",
    "realEstateAgentFees": "3427,2 €",
    "realEstateTransferTax": "1920 €",
    "notaryFee": "6240 €",
    "sumAdditionalPurchaseCost": "11.587,2 €",
    "overallPurchasePrice": "107.587,2 €",
    "bankLoan": "107.587,2 €",
    "initialRepayment": "1,00 %",
    "interestRate": "1,5 %",
    "equityCapital": "0 €",
    "creditRateYear": "2.690 €",
    "creditRateMonth": "224 €",
    "netRentYear": " 4800 €",
    "netRentMonth": "400 €",
    "maintenanceCostAndImprovementsFactor": "25 €",
    "managementFeeYear": "300 €",
    "vacancyRateFactor": "5 %",
    "pricePerSizeInclAdditionalCost": "3586,24 €",
    "netRentPerSizePerMonth": "13,33 €",
    "netRentPerSizePerYear": "159,96 €",
    "adjustedAnnualNetRent": "3.750 €" ,
    "adjustedNetReturn": "3,49 %",
    "maintenanceCostAndImprovementsYear": "750 €",
    "vacancyRate": "240 €",
    "improvementsMonth": "€",
    "improvementsYear": "€",
    "CFBTYear": "820 €",
    "CFBTMonth": "68 €"
  },
  {
    "id": "5",
    "image": "",
    "name": "DeinTraumHaus",
    "typ": "Haus",
    "address": {
      "street": "Entenstraße",
      "number": "5",
      "PLZ": "60323",
      "city": "Frankfurt am Main",
      "state": "Hessen"
    },
    "exposeURL": "https://google.de",
    "size": "30",
    "source": "Immobilienscout24",
    "contactPerson": "Donald Duck",
    "purchasePrice": "96000 €",
    "realEstateAgentFees": "3427,2 €",
    "realEstateTransferTax": "1920 €",
    "notaryFee": "6240 €",
    "sumAdditionalPurchaseCost": "11.587,2 €",
    "overallPurchasePrice": "107.587,2 €",
    "bankLoan": "107.587,2 €",
    "initialRepayment": "1,00 %",
    "interestRate": "1,5 %",
    "equityCapital": "0 €",
    "creditRateYear": "2.690 €",
    "creditRateMonth": "224 €",
    "netRentYear": " 4800 €",
    "netRentMonth": "400 €",
    "maintenanceCostAndImprovementsFactor": "25 €",
    "managementFeeYear": "300 €",
    "vacancyRateFactor": "5 %",
    "pricePerSizeInclAdditionalCost": "3586,24 €",
    "netRentPerSizePerMonth": "13,33 €",
    "netRentPerSizePerYear": "159,96 €",
    "adjustedAnnualNetRent": "3.750 €" ,
    "adjustedNetReturn": "3,49 %",
    "maintenanceCostAndImprovementsYear": "750 €",
    "vacancyRate": "240 €",
    "improvementsMonth": "€",
    "improvementsYear": "€",
    "CFBTYear": "820 €",
    "CFBTMonth": "68 €"
  }
]
